controller.v
module traffic_light_controller(
    input clk,
    input reset,
    input pred_NS,
    input pred_EW,
    input emergency_NS,
    input emergency_EW,
    output reg  [1:0] light_NS,
    output reg  [1:0] light_EW,
    output reg   pred_signal_NS,
    output reg   pred_signal_EW
);

parameter S0_NS_GREEN       = 3'd0;
parameter S1_NS_YELLOW      = 3'd1;
parameter S2_EW_GREEN       = 3'd2;
parameter S3_EW_YELLOW      = 3'd3;
parameter S4_EMERGENCY_NS   = 3'd4;
parameter S5_EMERGENCY_EW   = 3'd5;

reg [2:0] next_state, current_state;
reg [3:0] timer;

localparam GREEN_TIME      = 10;
localparam YELLOW_TIME     = 3;
localparam EMERGENCY_TIME  = 5;
localparam PED_EXTRA_TIME  = 3;

always @ (posedge clk or posedge reset)
begin
    if(reset)
    begin
        current_state <= S0_NS_GREEN;
        timer <= 0;
    end
    else
    begin
        if(
            (current_state == S0_NS_GREEN && timer == (pred_NS ? GREEN_TIME + PED_EXTRA_TIME : GREEN_TIME))||
            (current_state == S1_NS_YELLOW && timer == YELLOW_TIME)||
            (current_state == S2_EW_GREEN && timer == (pred_EW ? GREEN_TIME + PED_EXTRA_TIME : GREEN_TIME))||
            (current_state == S3_EW_YELLOW && timer == YELLOW_TIME)||
            (current_state == S4_EMERGENCY_NS && timer == EMERGENCY_TIME)||
            (current_state == S5_EMERGENCY_EW && timer == EMERGENCY_TIME)
        )
        begin
            current_state <= next_state;
            timer <= 0;
        end
        else
        begin
            timer <= timer+1;
        end
    end
end

always @ (*)
begin
    case(current_state)
    S0_NS_GREEN:
        if(emergency_EW)
            next_state = S5_EMERGENCY_EW;
        else
            next_state = S1_NS_YELLOW;

    S1_NS_YELLOW:
        if(emergency_EW)
            next_state = S5_EMERGENCY_EW;
        else
            next_state = S2_EW_GREEN;

    S2_EW_GREEN:
        if(emergency_NS)
            next_state = S4_EMERGENCY_NS;
        else
            next_state = S3_EW_YELLOW;

    S3_EW_YELLOW:
        if(emergency_NS)
            next_state = S4_EMERGENCY_NS;
        else
            next_state = S0_NS_GREEN;

    S4_EMERGENCY_NS:
        next_state = S2_EW_GREEN;

    S5_EMERGENCY_EW:            
        next_state = S0_NS_GREEN;

    default:       
        next_state = S0_NS_GREEN;
    endcase
end

always @ (*)
begin
    light_NS = 2'b00;
    light_EW = 2'b00;
    pred_signal_NS = 1'b0;
    pred_signal_EW = 1'b0;

    case(current_state)
    S0_NS_GREEN:begin
        light_NS = 2'b10;
        light_EW = 2'b00;
        pred_signal_NS = 1'b1;
    end
    S1_NS_YELLOW:begin
        light_NS = 2'b01;
        light_EW = 2'b00;
    end
    S2_EW_GREEN:begin
        light_NS = 2'b00;
        light_EW = 2'b10;
        pred_signal_EW = 1'b1;
    end
    S3_EW_YELLOW: begin
        light_NS = 2'b00;
        light_EW = 2'b01;
    end
    S4_EMERGENCY_NS : begin
        light_NS = 2'b10;
        light_EW = 2'b00;
    end
    S5_EMERGENCY_EW : begin
        light_NS = 2'b00;
        light_EW = 2'b10;
    end
    endcase
end 

endmodule

tb_controller.v
`timescale 1ns/1ps

module tb_traffic_light_controller;

    reg clk;
    reg reset;
    reg pred_NS;
    reg pred_EW;
    reg emergency_NS;
    reg emergency_EW;
    wire [1:0] light_NS;
    wire [1:0] light_EW;
    wire pred_signal_NS;
    wire pred_signal_EW;

    traffic_light_controller dut (
        .clk(clk),
        .reset(reset),
        .pred_NS(pred_NS),
        .pred_EW(pred_EW),
        .emergency_NS(emergency_NS),
        .emergency_EW(emergency_EW),
        .light_NS(light_NS),
        .light_EW(light_EW),
        .pred_signal_NS(pred_signal_NS),
        .pred_signal_EW(pred_signal_EW)
    );

    always #5 clk = ~clk;

    initial begin
        $dumpfile("traffic_light.vcd");
        $dumpvars(0, tb_traffic_light_controller);

        clk = 0;
        reset = 1;
        pred_NS = 0;
        pred_EW = 0;
        emergency_NS = 0;
        emergency_EW = 0;

        #20 reset = 0;

        #50 pred_NS = 1;
        #100 pred_NS = 0;

        #100 emergency_EW = 1;
        #50 emergency_EW = 0;

        #200 pred_EW = 1;
        #100 pred_EW = 0;

        #100 emergency_NS = 1;
        #50 emergency_NS = 0;

        #300 $finish;
    end

endmodule

traffic_light.vcd
$date
	Sat Jul 12 23:19:09 2025
$end
$version
	Icarus Verilog
$end
$timescale
	1ps
$end
$scope module tb_traffic_light_controller $end
$var wire 1 ! pred_signal_NS $end
$var wire 1 " pred_signal_EW $end
$var wire 2 # light_NS [1:0] $end
$var wire 2 $ light_EW [1:0] $end
$var reg 1 % clk $end
$var reg 1 & emergency_EW $end
$var reg 1 ' emergency_NS $end
$var reg 1 ( pred_EW $end
$var reg 1 ) pred_NS $end
$var reg 1 * reset $end
$scope module dut $end
$var wire 1 % clk $end
$var wire 1 & emergency_EW $end
$var wire 1 ' emergency_NS $end
$var wire 1 ( pred_EW $end
$var wire 1 ) pred_NS $end
$var wire 1 * reset $end
$var parameter 32 + EMERGENCY_TIME $end
$var parameter 32 , GREEN_TIME $end
$var parameter 32 - PED_EXTRA_TIME $end
$var parameter 3 . S0_NS_GREEN $end
$var parameter 3 / S1_NS_YELLOW $end
$var parameter 3 0 S2_EW_GREEN $end
$var parameter 3 1 S3_EW_YELLOW $end
$var parameter 3 2 S4_EMERGENCY_NS $end
$var parameter 3 3 S5_EMERGENCY_EW $end
$var parameter 32 4 YELLOW_TIME $end
$var reg 3 5 current_state [2:0] $end
$var reg 2 6 light_EW [1:0] $end
$var reg 2 7 light_NS [1:0] $end
$var reg 3 8 next_state [2:0] $end
$var reg 1 " pred_signal_EW $end
$var reg 1 ! pred_signal_NS $end
$var reg 4 9 timer [3:0] $end
$upscope $end
$upscope $end
$enddefinitions $end
$comment Show the parameter values. $end
$dumpall
b11 4
b101 3
b100 2
b11 1
b10 0
b1 /
b0 .
b11 -
b1010 ,
b101 +
$end
#0
$dumpvars
b0 9
b1 8
b10 7
b0 6
b0 5
1*
0)
0(
0'
0&
0%
b0 $
b10 #
0"
1!
$end
#5000
1%
#10000
0%
#15000
1%
#20000
0%
0*
#25000
b1 9
1%
#30000
0%
#35000
b10 9
1%
#40000
0%
#45000
b11 9
1%
#50000
0%
#55000
b100 9
1%
#60000
0%
#65000
b101 9
1%
#70000
0%
1)
#75000
b110 9
1%
#80000
0%
#85000
b111 9
1%
#90000
0%
#95000
b1000 9
1%
#100000
0%
#105000
b1001 9
1%
#110000
0%
#115000
b1010 9
1%
#120000
0%
#125000
b1011 9
1%
#130000
0%
#135000
b1100 9
1%
#140000
0%
#145000
b1101 9
1%
#150000
0%
#155000
0!
b1 #
b1 7
b10 8
b0 9
b1 5
1%
#160000
0%
#165000
b1 9
1%
#170000
0%
0)
#175000
b10 9
1%
#180000
0%
#185000
b11 9
1%
#190000
0%
#195000
1"
b10 $
b10 6
b0 #
b0 7
b11 8
b0 9
b10 5
1%
#200000
0%
#205000
b1 9
1%
#210000
0%
#215000
b10 9
1%
#220000
0%
#225000
b11 9
1%
#230000
0%
#235000
b100 9
1%
#240000
0%
#245000
b101 9
1%
#250000
0%
#255000
b110 9
1%
#260000
0%
#265000
b111 9
1%
#270000
0%
1&
#275000
b1000 9
1%
#280000
0%
#285000
b1001 9
1%
#290000
0%
#295000
b1010 9
1%
#300000
0%
#305000
0"
b1 $
b1 6
b0 8
b0 9
b11 5
1%
#310000
0%
#315000
b1 9
1%
#320000
0%
0&
#325000
b10 9
1%
#330000
0%
#335000
b11 9
1%
#340000
0%
#345000
1!
b10 #
b10 7
b0 $
b0 6
b1 8
b0 9
b0 5
1%
#350000
0%
#355000
b1 9
1%
#360000
0%
#365000
b10 9
1%
#370000
0%
#375000
b11 9
1%
#380000
0%
#385000
b100 9
1%
#390000
0%
#395000
b101 9
1%
#400000
0%
#405000
b110 9
1%
#410000
0%
#415000
b111 9
1%
#420000
0%
#425000
b1000 9
1%
#430000
0%
#435000
b1001 9
1%
#440000
0%
#445000
b1010 9
1%
#450000
0%
#455000
0!
b1 #
b1 7
b10 8
b0 9
b1 5
1%
#460000
0%
#465000
b1 9
1%
#470000
0%
#475000
b10 9
1%
#480000
0%
#485000
b11 9
1%
#490000
0%
#495000
1"
b10 $
b10 6
b0 #
b0 7
b11 8
b0 9
b10 5
1%
#500000
0%
#505000
b1 9
1%
#510000
0%
#515000
b10 9
1%
#520000
0%
1(
#525000
b11 9
1%
#530000
0%
#535000
b100 9
1%
#540000
0%
#545000
b101 9
1%
#550000
0%
#555000
b110 9
1%
#560000
0%
#565000
b111 9
1%
#570000
0%
#575000
b1000 9
1%
#580000
0%
#585000
b1001 9
1%
#590000
0%
#595000
b1010 9
1%
#600000
0%
#605000
b1011 9
1%
#610000
0%
#615000
b1100 9
1%
#620000
0%
0(
#625000
b1101 9
1%
#630000
0%
#635000
b1110 9
1%
#640000
0%
#645000
b1111 9
1%
#650000
0%
#655000
b0 9
1%
#660000
0%
#665000
b1 9
1%
#670000
0%
#675000
b10 9
1%
#680000
0%
#685000
b11 9
1%
#690000
0%
#695000
b100 9
1%
#700000
0%
#705000
b101 9
1%
#710000
0%
#715000
b110 9
1%
#720000
b100 8
0%
1'
#725000
b111 9
1%
#730000
0%
#735000
b1000 9
1%
#740000
0%
#745000
b1001 9
1%
#750000
0%
#755000
b1010 9
1%
#760000
0%
#765000
b10 #
b10 7
0"
b0 $
b0 6
b10 8
b0 9
b100 5
1%
#770000
0%
0'
#775000
b1 9
1%
#780000
0%
#785000
b10 9
1%
#790000
0%
#795000
b11 9
1%
#800000
0%
#805000
b100 9
1%
#810000
0%
#815000
b101 9
1%
#820000
0%
#825000
1"
b10 $
b10 6
b0 #
b0 7
b11 8
b0 9
b10 5
1%
#830000
0%
#835000
b1 9
1%
#840000
0%
#845000
b10 9
1%
#850000
0%
#855000
b11 9
1%
#860000
0%
#865000
b100 9
1%
#870000
0%
#875000
b101 9
1%
#880000
0%
#885000
b110 9
1%
#890000
0%
#895000
b111 9
1%
#900000
0%
#905000
b1000 9
1%
#910000
0%
#915000
b1001 9
1%
#920000
0%
#925000
b1010 9
1%
#930000
0%
#935000
0"
b1 $
b1 6
b0 8
b0 9
b11 5
1%
#940000
0%
#945000
b1 9
1%
#950000
0%
#955000
b10 9
1%
#960000
0%
#965000
b11 9
1%
#970000
0%
#975000
1!
b10 #
b10 7
b0 $
b0 6
b1 8
b0 9
b0 5
1%
#980000
0%
#985000
b1 9
1%
#990000
0%
#995000
b10 9
1%
#1000000
0%
#1005000
b11 9
1%
#1010000
0%
#1015000
b100 9
1%
#1020000
0%
#1025000
b101 9
1%
#1030000
0%
#1035000
b110 9
1%
#1040000
0%
#1045000
b111 9
1%
#1050000
0%
#1055000
b1000 9
1%
#1060000
0%
#1065000
b1001 9
1%
